OpenSpecimenAPIconnector/__init__.py
OpenSpecimenAPIconnector/config.py
OpenSpecimenAPIconnector/mg_core/__init__.py
OpenSpecimenAPIconnector/mg_core/mappings.py
OpenSpecimenAPIconnector/mg_util/OpenSpecimenBBMRImapping.py
OpenSpecimenAPIconnector/mg_util/__init__.py
OpenSpecimenAPIconnector/os_core/__init__.py
OpenSpecimenAPIconnector/os_core/collection_protocol.py
OpenSpecimenAPIconnector/os_core/collection_protocol_event.py
OpenSpecimenAPIconnector/os_core/collection_protocol_registration.py
OpenSpecimenAPIconnector/os_core/container.py
OpenSpecimenAPIconnector/os_core/csv_bulk.py
OpenSpecimenAPIconnector/os_core/csv_export.py
OpenSpecimenAPIconnector/os_core/form.py
OpenSpecimenAPIconnector/os_core/institute.py
OpenSpecimenAPIconnector/os_core/jsons.py
OpenSpecimenAPIconnector/os_core/lists.py
OpenSpecimenAPIconnector/os_core/mandatory.py
OpenSpecimenAPIconnector/os_core/participant.py
OpenSpecimenAPIconnector/os_core/query.py
OpenSpecimenAPIconnector/os_core/req_util.py
OpenSpecimenAPIconnector/os_core/site.py
OpenSpecimenAPIconnector/os_core/specimen.py
OpenSpecimenAPIconnector/os_core/specimen_event.py
OpenSpecimenAPIconnector/os_core/url.py
OpenSpecimenAPIconnector/os_core/users.py
OpenSpecimenAPIconnector/os_core/visit.py
OpenSpecimenAPIconnector/os_util/__init__.py
OpenSpecimenAPIconnector/os_util/aggregated_fields.py
OpenSpecimenAPIconnector/os_util/bulk_operations.py
OpenSpecimenAPIconnector/os_util/collection_protocol_util.py
OpenSpecimenAPIconnector/os_util/container_util.py
OpenSpecimenAPIconnector/os_util/cpevent_util.py
OpenSpecimenAPIconnector/os_util/cpr_util.py
OpenSpecimenAPIconnector/os_util/csv_exp_util.py
OpenSpecimenAPIconnector/os_util/institute_util.py
OpenSpecimenAPIconnector/os_util/query_util.py
OpenSpecimenAPIconnector/os_util/site_util.py
OpenSpecimenAPIconnector/os_util/specimen_util.py
OpenSpecimenAPIconnector/os_util/users_util.py
OpenSpecimenAPIconnector/os_util/visit_util.py
OpenSpecimenAPIconnector-0.9.4.dist-info/LICENSE.txt
OpenSpecimenAPIconnector-0.9.4.dist-info/METADATA
OpenSpecimenAPIconnector-0.9.4.dist-info/WHEEL
OpenSpecimenAPIconnector-0.9.4.dist-info/top_level.txt
OpenSpecimenAPIconnector-0.9.4.dist-info/RECORD
