Metadata-Version: 2.1
Name: OpenSpecimenAPIconnector
Version: 0.9.4
Summary: Python API commands to interact with OpenSpecimen
Home-page: https://github.com/bibbox/OpenSpecimenAPIconnector.py/tree/master
Author: Christam Schorn and Simon Streit
Author-email: simon.streit@medunigraz.at
License: BSD 2-clause
Keywords: Openspecimen,API,Python Openspecimen
Classifier: Development Status :: 2 - Pre-Alpha
Classifier: Intended Audience :: Developers
Classifier: Topic :: Software Development
Classifier: License :: OSI Approved :: BSD License
Classifier: Operating System :: POSIX :: Linux
Classifier: Programming Language :: Python :: 3
Classifier: Programming Language :: Python :: 3.4
Classifier: Programming Language :: Python :: 3.6
Classifier: Programming Language :: Python :: 3.8
Classifier: Programming Language :: Python :: 3.9
License-File: LICENSE.txt
Requires-Dist: pandas
Requires-Dist: numpy
Requires-Dist: requests
Requires-Dist: faker
Requires-Dist: names
Requires-Dist: xlsxwriter
Requires-Dist: openpyxl
